pytorch_ranger/__init__.py
pytorch_ranger/ranger.py
pytorch_ranger/ranger913A.py
pytorch_ranger/rangerqh.py
pytorch_ranger/types.py
pytorch_ranger-0.1.1.dist-info/LICENSE
pytorch_ranger-0.1.1.dist-info/METADATA
pytorch_ranger-0.1.1.dist-info/WHEEL
pytorch_ranger-0.1.1.dist-info/top_level.txt
pytorch_ranger-0.1.1.dist-info/RECORD
